{
  "flashcards": {
    "6-2-1": {
      "replace_all": true,
      "items": [
        {
          "front": "What divergence is required to use the initial nonradar departure minima on diverging courses?",
          "back": "The aircraft must depart the same or adjacent airports and fly courses diverging by 45 degrees or more.",
          "card_type": "definition"
        }
      ]
    },
    "6-2-2": {
      "replace_all": true,
      "items": [
        {
          "front": "How are same-course departures separated when the following aircraft will climb through the leading aircraft's altitude?",
          "back": "Use 3 minutes until the following aircraft passes through the leading aircraft's assigned altitude, or 5 miles between eligible DME or ATD aircraft.",
          "card_type": "procedure"
        }
      ]
    }
  }
}
