{
  "flashcards": {
    "5-1-6": {
      "replace_all": true,
      "items": [
        {
          "front": "When is a deviation advisory issued?",
          "back": "When the aircraft is observed in a position and on a track that will obviously cause it to deviate from protected airspace.",
          "card_type": "requirement"
        },
        {
          "front": "If necessary, what should ATC do after issuing a deviation advisory?",
          "back": "Help the aircraft return to the assigned protected airspace.",
          "card_type": "requirement"
        },
        {
          "front": "What is the total width of an RNAV ATS route described in the note?",
          "back": "8 miles.",
          "card_type": "definition"
        },
        {
          "front": "How much laterally protected airspace exists on each side of an RNAV ATS route centerline?",
          "back": "4 miles on each side.",
          "card_type": "definition"
        },
        {
          "front": "What route-centerline performance are aircraft on RNAV ATS routes expected to maintain?",
          "back": "Within 2 miles of the route centerline.",
          "card_type": "requirement"
        },
        {
          "front": "What may be indicated by an aircraft approaching the 2-mile RNAV centerline limit?",
          "back": "A navigation system error or failure.",
          "card_type": "definition"
        }
      ]
    },
    "5-1-7": {
      "replace_all": true,
      "items": [
        {
          "front": "When must a fix time be manually recorded?",
          "back": "At least once for each controlled aircraft in the sector when the EAS FDP flight progress recording components are not operational.",
          "card_type": "requirement"
        },
        {
          "front": "What type of operation does this manual fix posting rule address?",
          "back": "En route operations.",
          "card_type": "scope"
        },
        {
          "front": "What aircraft does this rule apply to?",
          "back": "Controlled aircraft in the controller's sector of responsibility.",
          "card_type": "scope"
        },
        {
          "front": "What system condition triggers this manual fix posting requirement?",
          "back": "The EAS FDP flight progress recording components are not operational.",
          "card_type": "requirement"
        },
        {
          "front": "How often must the observed or reported fix time be manually recorded for each controlled aircraft when this rule is active?",
          "back": "At least once.",
          "card_type": "requirement"
        }
      ]
    },
    "5-1-8": {
      "replace_all": true,
      "items": [
        {
          "front": "When may ATC request an estimate or report over a specific fix?",
          "back": "When necessary.",
          "card_type": "requirement"
        },
        {
          "front": "After ATC states \"radar contact,\" what happens to compulsory reporting over reporting points?",
          "back": "It is discontinued.",
          "card_type": "requirement"
        },
        {
          "front": "When does normal position reporting resume after radar contact has been established?",
          "back": "When ATC informs the aircraft \"radar contact lost\" or \"radar service terminated.\"",
          "card_type": "requirement"
        },
        {
          "front": "Name one published position-report request from this paragraph.",
          "back": "Over/passing (fix), miles from (fix), miles direction of (fix/airway/location), crossing/joining/departing (airway or route), or intercepting/crossing a named NAVAID radial.",
          "card_type": "phraseology"
        },
        {
          "front": "Does radar contact permanently bar the controller from requesting a specific fix report?",
          "back": "No.",
          "card_type": "exception"
        },
        {
          "front": "What statement from ATC causes compulsory position reporting to stop?",
          "back": "\"Radar contact.\"",
          "card_type": "phraseology"
        }
      ]
    },
    "5-1-9": {
      "replace_all": true,
      "items": [
        {
          "front": "What must generally be done when radar service is terminated?",
          "back": "Inform the aircraft that radar service is terminated.",
          "card_type": "requirement"
        },
        {
          "front": "What phraseology is used to terminate radar service?",
          "back": "Radar service terminated. Add nonradar routing if required.",
          "card_type": "phraseology"
        },
        {
          "front": "Name one situation in which radar service is automatically terminated and the aircraft need not be separately advised.",
          "back": "Cancellation of IFR outside the listed radar-service areas, or an aircraft on an instrument/visual/contact approach has landed or has been instructed to change to advisory frequency.",
          "card_type": "exception"
        },
        {
          "front": "At a tower-controlled airport where radar coverage does not exist to within one-half mile of the runway end, what must be done for arriving aircraft?",
          "back": "They must be informed when radar service is terminated.",
          "card_type": "requirement"
        },
        {
          "front": "Does IFR cancellation inside Class B, Class C, TRSA, or where basic radar service is provided automatically terminate radar service without further advisory?",
          "back": "No.",
          "card_type": "exception"
        },
        {
          "front": "If an aircraft has been instructed to change to advisory frequency while conducting an instrument, visual, or contact approach, what happens to radar service?",
          "back": "It is automatically terminated.",
          "card_type": "exception"
        }
      ]
    }
  }
}
