{
  "flashcards": {
    "8-2-1": {
      "replace_all": true,
      "items": [
        {
          "front": "What coordination updates must ARTCCs forward in oceanic operations?",
          "back": "Forward current flight plan and control information, coordinate in time for receiving-facility action, and forward estimate revisions of 3 minutes or more.",
          "card_type": "procedure"
        }
      ]
    },
    "8-2-2": {
      "replace_all": true,
      "items": [
        {
          "front": "When is transfer of air-ground communications made when nonradar separation is being applied?",
          "back": "Make the transfer 5 minutes before the aircraft reaches the boundary unless the facilities agree otherwise.",
          "card_type": "procedure"
        }
      ]
    },
    "8-2-3": {
      "replace_all": true,
      "items": [
        {
          "front": "How is AIDC coordination accomplished where interfacility data communications are implemented?",
          "back": "Use regional Interface Control Documents supported by letters of agreement between the facilities concerned.",
          "card_type": "definition"
        }
      ]
    }
  }
}
